MANIFEST.in
README.md
setup.py
mmgui/__init__.py
mmgui/app.py
mmgui/asyncqt.py
mmgui/menu.py
mmgui/platform.py
mmgui/res.qrc
mmgui/res_rc.py
mmgui/webview.py
mmgui/webview_window_ui.py
mmgui/webview_window_ui.ui
mmgui.egg-info/PKG-INFO
mmgui.egg-info/SOURCES.txt
mmgui.egg-info/dependency_links.txt
mmgui.egg-info/not-zip-safe
mmgui.egg-info/requires.txt
mmgui.egg-info/top_level.txt
mmgui/__pycache__/__init__.cpython-37.pyc
mmgui/__pycache__/app.cpython-37.pyc
mmgui/__pycache__/asyncqt.cpython-37.pyc
mmgui/__pycache__/menu.cpython-37.pyc
mmgui/__pycache__/platform.cpython-37.pyc
mmgui/__pycache__/res_rc.cpython-37.pyc
mmgui/__pycache__/webview.cpython-37.pyc
mmgui/__pycache__/webview_window_ui.cpython-37.pyc
mmgui/res/images/icon.png
mmgui/res/images/splash.png
mmgui/res/js/mmgui.js
mmgui/res/js/qwebchannel.js
tests/__init__.py
tests/webview_test.py