Metadata-Version: 1.2
Name: mmgui
Version: 0.0.1
Summary: mmgui
Home-page: http://gitlab.testplus.cn/sandin/mmgui
Author: lds2012
Author-email: lds2012@gmail.com
License: GPLv3
Platform: UNKNOWN
Requires-Python: >=3.6
